downloadbuffer/__init__.py
downloadbuffer-0.1.4.dist-info/DESCRIPTION.rst
downloadbuffer-0.1.4.dist-info/METADATA
downloadbuffer-0.1.4.dist-info/RECORD
downloadbuffer-0.1.4.dist-info/WHEEL
downloadbuffer-0.1.4.dist-info/metadata.json
downloadbuffer-0.1.4.dist-info/top_level.txt
