Metadata-Version: 2.0
Name: downloadbuffer
Version: 0.1.4
Summary: Stream and buffer large files via HTTP
Home-page: https://github.com/NickAnderegg/downloadbuffer
Author: Nick Anderegg
Author-email: nick@anderegg.io
License: GPLv3
Platform: UNKNOWN
Classifier: Development Status :: 3 - Alpha
Classifier: License :: OSI Approved :: GNU General Public License v3 (GPLv3)
Classifier: Natural Language :: English
Classifier: Intended Audience :: Developers
Classifier: Programming Language :: Python
Classifier: Programming Language :: Python :: 3
Classifier: Programming Language :: Python :: 3.3
Classifier: Programming Language :: Python :: 3.4
Classifier: Programming Language :: Python :: 3.5
Classifier: Programming Language :: Python :: 3 :: Only
Classifier: Programming Language :: Python :: Implementation :: CPython
Requires-Dist: queueio
Requires-Dist: requests
